MANIFEST.in
setup.py
injson_check/__init__.py
injson_check/injson_check.py
injson_check/xlibz.py
injson_check.egg-info/PKG-INFO
injson_check.egg-info/SOURCES.txt
injson_check.egg-info/dependency_links.txt
injson_check.egg-info/top_level.txt