Metadata-Version: 2.1
Name: injson-check
Version: 0.3.3
Summary: 数据校验器：injson同版本替代 可正常使用
Home-page: https://github.com/
Author: liyubin
Author-email: 1399393088@qq.com
License: MIT Licence
Keywords: pip,injson_check,featureextraction
Platform: any
